ansible_lint_custom_strict_naming/__about__.py
ansible_lint_custom_strict_naming/__init__.py
ansiblelint/rules/custom/ansible_lint_custom_strict_naming/__init__.py
ansiblelint/rules/custom/ansible_lint_custom_strict_naming/debug.py
ansiblelint/rules/custom/ansible_lint_custom_strict_naming/register_prefix.py
ansiblelint/rules/custom/ansible_lint_custom_strict_naming/var_name_prefix.py
ansible_lint_custom_strict_naming-1.1.2.dist-info/LICENSE
ansible_lint_custom_strict_naming-1.1.2.dist-info/METADATA
ansible_lint_custom_strict_naming-1.1.2.dist-info/WHEEL
ansible_lint_custom_strict_naming-1.1.2.dist-info/top_level.txt
ansible_lint_custom_strict_naming-1.1.2.dist-info/RECORD
