Metadata-Version: 2.1
Name: ansible-lint-custom-strict-naming
Version: 1.1.2
Summary: Add your description here
Author-email: pollenjp <polleninjp@gmail.com>
Project-URL: Homepage, https://github.com/pollenjp/ansible-lint-custom-strict-naming
Project-URL: Repository, https://github.com/pollenjp/ansible-lint-custom-strict-naming
Classifier: Development Status :: 1 - Planning
Classifier: Programming Language :: Python :: 3
Classifier: Programming Language :: Python :: 3.12
Requires-Python: >=3.12
License-File: LICENSE
Requires-Dist: ansible-lint>=6.24.0
